design/acsu.v
module acsu (
    // Inputs from BMU
    input wire [1:0] bm_s0_s0_i, bm_s0_s2_i,
    input wire [1:0] bm_s1_s0_i, bm_s1_s2_i,
    input wire [1:0] bm_s2_s1_i, bm_s2_s3_i,
    input wire [1:0] bm_s3_s1_i, bm_s3_s3_i,

    // Inputs from PMU (Old path metrics)
    input wire [7:0] pm_s0_i, pm_s1_i, pm_s2_i, pm_s3_i,

    // Outputs
    output reg [3:0] dec_bits_o,
    output reg [7:0] pm_s0_o, pm_s1_o, pm_s2_o, pm_s3_o
);

    reg [7:0] path0_cand0, path0_cand1;
    reg [7:0] path1_cand0, path1_cand1;
    reg [7:0] path2_cand0, path2_cand1;
    reg [7:0] path3_cand0, path3_cand1;

    // Replace always @(*) with full sensitivity list
    always @(bm_s0_s0_i, bm_s0_s2_i, bm_s1_s0_i, bm_s1_s0_i, 
             bm_s2_s1_i, bm_s2_s3_i, bm_s3_s1_i, bm_s3_s3_i,
             pm_s0_i, pm_s1_i, pm_s2_i, pm_s3_i,
             path0_cand0, path0_cand1, path1_cand0, path1_cand1,
             path2_cand0, path2_cand1, path3_cand0, path3_cand1) begin

               // --- Calculation for State 0 ---
        path0_cand0 = pm_s0_i + bm_s0_s0_i;
        path0_cand1 = pm_s1_i + bm_s1_s0_i;
                // --- Calculation for State 1 ---
        path1_cand0 = pm_s2_i + bm_s2_s1_i;
        path1_cand1 = pm_s3_i + bm_s3_s1_i;
                // --- Calculation for State 2 ---
        path2_cand0 = pm_s0_i + bm_s0_s2_i;
        path2_cand1 = pm_s1_i + bm_s1_s2_i;
                // --- Calculation for State 3 ---
        path3_cand0 = pm_s2_i + bm_s2_s3_i;
        path3_cand1 = pm_s3_i + bm_s3_s3_i;
        // Assign default values (Equivalent to default in case)
        // Ensure output is always defined even if if-else logic has gaps
        dec_bits_o = 4'b0000;
        pm_s0_o    = 8'hFF;
        pm_s1_o    = 8'hFF;
        pm_s2_o    = 8'hFF;
        pm_s3_o    = 8'hFF;
        

        if (path0_cand0 <= path0_cand1) begin
            pm_s0_o = path0_cand0;
            dec_bits_o[0] = 1'b0;
        end else begin
            pm_s0_o = path0_cand1;
            dec_bits_o[0] = 1'b1;
        end

        if (path1_cand0 <= path1_cand1) begin
            pm_s1_o = path1_cand0;
            dec_bits_o[1] = 1'b0;
        end else begin
            pm_s1_o = path1_cand1;
            dec_bits_o[1] = 1'b1;
        end

        if (path2_cand0 <= path2_cand1) begin
            pm_s2_o = path2_cand0;
            dec_bits_o[2] = 1'b0;
        end else begin
            pm_s2_o = path2_cand1;
            dec_bits_o[2] = 1'b1;
        end

        if (path3_cand0 <= path3_cand1) begin
            pm_s3_o = path3_cand0;
            dec_bits_o[3] = 1'b0;
        end else begin
            pm_s3_o = path3_cand1;
            dec_bits_o[3] = 1'b1;
        end
    end

endmodule

testbench/tb_acsu.sv
`timescale 1ns / 1ps
`include "../design/acsu.v"
module acsu_full_check_tb();

    // Tin hieu ket noi
    reg [1:0] bm_s0_s0, bm_s0_s2, bm_s1_s0, bm_s1_s2;
    reg [1:0] bm_s2_s1, bm_s2_s3, bm_s3_s1, bm_s3_s3;
    reg [7:0] pm_s0_i, pm_s1_i, pm_s2_i, pm_s3_i;

    wire [3:0] dec_bits_o;
    wire [7:0] pm_s0_o, pm_s1_o, pm_s2_o, pm_s3_o;

    integer j, error_count;
    reg [7:0] exp_pm [0:3];
    reg [3:0] exp_dec;

    // Khoi tao DUT
    acsu uut (
        .bm_s0_s0_i(bm_s0_s0), .bm_s0_s2_i(bm_s0_s2), .bm_s1_s0_i(bm_s1_s0), .bm_s1_s2_i(bm_s1_s2),
        .bm_s2_s1_i(bm_s2_s1), .bm_s2_s3_i(bm_s2_s3), .bm_s3_s1_i(bm_s3_s1), .bm_s3_s3_i(bm_s3_s3),
        .pm_s0_i(pm_s0_i), .pm_s1_i(pm_s1_i), .pm_s2_i(pm_s2_i), .pm_s3_i(pm_s3_i),
        .dec_bits_o(dec_bits_o),
        .pm_s0_o(pm_s0_o), .pm_s1_o(pm_s1_o), .pm_s2_o(pm_s2_o), .pm_s3_o(pm_s3_o)
    );

    // Golden Model
    task calculate_expected;
        reg [7:0] c0, c1;
        begin
            c0 = pm_s0_i + bm_s0_s0; c1 = pm_s1_i + bm_s1_s0;
            exp_pm[0] = (c0 <= c1) ? c0 : c1; exp_dec[0] = (c0 <= c1) ? 1'b0 : 1'b1;
            
            c0 = pm_s2_i + bm_s2_s1; c1 = pm_s3_i + bm_s3_s1;
            exp_pm[1] = (c0 <= c1) ? c0 : c1; exp_dec[1] = (c0 <= c1) ? 1'b0 : 1'b1;
            
            c0 = pm_s0_i + bm_s0_s2; c1 = pm_s1_i + bm_s1_s2;
            exp_pm[2] = (c0 <= c1) ? c0 : c1; exp_dec[2] = (c0 <= c1) ? 1'b0 : 1'b1;
            
            c0 = pm_s2_i + bm_s2_s3; c1 = pm_s3_i + bm_s3_s3;
            exp_pm[3] = (c0 <= c1) ? c0 : c1; exp_dec[3] = (c0 <= c1) ? 1'b0 : 1'b1;
        end
    endtask

    // Task hien thi chi tiet da PASS hay FAIL
    task verify_all;
        input [8*20:1] scenario;
        begin
            calculate_expected();
            #1; // Cho mach to hop
            
            if (dec_bits_o === exp_dec && 
                pm_s0_o === exp_pm[0] && pm_s1_o === exp_pm[1] && 
                pm_s2_o === exp_pm[2] && pm_s3_o === exp_pm[3]) 
                $display("[%0t ns] [PASS] %s", $time, scenario);
            else begin
                $display("[%0t ns] [FAIL] %s", $time, scenario);
                error_count = error_count + 1;
            end

            // Luon luon hien thi bang so sanh de chup anh bao cao
            $display("      --------------------------------------------------");
            $display("      Output |   Got   | Expected | Status");
            $display("      -------|---------|----------|---------");
            $display("      DEC    |  %b   |   %b   | %s", dec_bits_o, exp_dec, (dec_bits_o === exp_dec) ? "OK" : "ERR");
            $display("      PM0    |  %d   |   %d   | %s", pm_s0_o, exp_pm[0], (pm_s0_o === exp_pm[0]) ? "OK" : "ERR");
            $display("      PM1    |  %d   |   %d   | %s", pm_s1_o, exp_pm[1], (pm_s1_o === exp_pm[1]) ? "OK" : "ERR");
            $display("      PM2    |  %d   |   %d   | %s", pm_s2_o, exp_pm[2], (pm_s2_o === exp_pm[2]) ? "OK" : "ERR");
            $display("      PM3    |  %d   |   %d   | %s", pm_s3_o, exp_pm[3], (pm_s3_o === exp_pm[3]) ? "OK" : "ERR");
            $display("      --------------------------------------------------");
        end
    endtask

    initial begin
        error_count = 0;
        {bm_s0_s0, bm_s0_s2, bm_s1_s0, bm_s1_s2, bm_s2_s1, bm_s2_s3, bm_s3_s1, bm_s3_s3} = 16'h0;
        {pm_s0_i, pm_s1_i, pm_s2_i, pm_s3_i} = 32'h0;

        $display("=========================================================");
        $display("START ACSU FULL REPORT: TIMING - GOT - EXPECTED");
        $display("=========================================================");

        // Kich ban 1: Min Path (5 lan)
        for(j=1; j<=5; j=j+1) begin
            pm_s0_i=10*j; pm_s1_i=5*j; pm_s2_i=20*j; pm_s3_i=15*j;
            bm_s0_s0=1; bm_s1_s0=1; bm_s2_s1=1; bm_s3_s1=1;
            #10 verify_all("Min Path Case");
        end

        // Kich ban 2: Toggling Winner (5 lan) - Doi tu nhanh 0 sang nhanh 1 thang
        for(j=1; j<=5; j=j+1) begin
            pm_s0_i=(j<3)? 5 : 50; pm_s1_i=(j<3)? 50 : 5;
            bm_s0_s0=2; bm_s1_s0=2;
            #10 verify_all("Switching Winner");
        end

        // Kich ban 3: High Metric (Gan tran 8-bit)
        for(j=1; j<=5; j=j+1) begin
            pm_s0_i=250; pm_s1_i=250; bm_s0_s0=j; bm_s1_s0=0;
            #10 verify_all("Boundary Case");
        end

        // Kich ban 4: Zero Inputs
        for(j=1; j<=5; j=j+1) begin
            {pm_s0_i, pm_s1_i, pm_s2_i, pm_s3_i} = 32'h0;
            {bm_s0_s0, bm_s1_s0, bm_s2_s1, bm_s3_s1} = 8'h0;
            #10 verify_all("Zero Case");
        end

        // Kich ban 5: Hoan toan ngau nhien
        for(j=1; j<=5; j=j+1) begin
            pm_s0_i=$random; pm_s1_i=$random; pm_s2_i=$random; pm_s3_i=$random;
            bm_s0_s0=$random; bm_s1_s0=$random; bm_s2_s1=$random; bm_s3_s1=$random;
            bm_s0_s2=$random; bm_s1_s2=$random; bm_s2_s3=$random; bm_s3_s3=$random;
            #10 verify_all("Random Stress");
        end
        
        $display("\n=========================================================");
        $display("FINAL TOTAL ERRORS: %0d", error_count);
        $display("=========================================================");
        $finish;
    end

    initial begin
        $dumpfile("acsu.vcd"); // Ten file du lieu song
        $dumpvars(0, acsu_full_check_tb); 
    end
endmodule

testbench/acsu.vcd
$date
	Sat Jan 24 08:16:22 2026
$end
$version
	Icarus Verilog
$end
$timescale
	1ps
$end
$scope module acsu_full_check_tb $end
$var wire 8 ! pm_s3_o [7:0] $end
$var wire 8 " pm_s2_o [7:0] $end
$var wire 8 # pm_s1_o [7:0] $end
$var wire 8 $ pm_s0_o [7:0] $end
$var wire 4 % dec_bits_o [3:0] $end
$var reg 2 & bm_s0_s0 [1:0] $end
$var reg 2 ' bm_s0_s2 [1:0] $end
$var reg 2 ( bm_s1_s0 [1:0] $end
$var reg 2 ) bm_s1_s2 [1:0] $end
$var reg 2 * bm_s2_s1 [1:0] $end
$var reg 2 + bm_s2_s3 [1:0] $end
$var reg 2 , bm_s3_s1 [1:0] $end
$var reg 2 - bm_s3_s3 [1:0] $end
$var reg 4 . exp_dec [3:0] $end
$var reg 8 / pm_s0_i [7:0] $end
$var reg 8 0 pm_s1_i [7:0] $end
$var reg 8 1 pm_s2_i [7:0] $end
$var reg 8 2 pm_s3_i [7:0] $end
$var integer 32 3 error_count [31:0] $end
$var integer 32 4 j [31:0] $end
$scope module uut $end
$var wire 2 5 bm_s0_s0_i [1:0] $end
$var wire 2 6 bm_s0_s2_i [1:0] $end
$var wire 2 7 bm_s1_s0_i [1:0] $end
$var wire 2 8 bm_s1_s2_i [1:0] $end
$var wire 2 9 bm_s2_s1_i [1:0] $end
$var wire 2 : bm_s2_s3_i [1:0] $end
$var wire 2 ; bm_s3_s1_i [1:0] $end
$var wire 2 < bm_s3_s3_i [1:0] $end
$var wire 8 = pm_s0_i [7:0] $end
$var wire 8 > pm_s1_i [7:0] $end
$var wire 8 ? pm_s2_i [7:0] $end
$var wire 8 @ pm_s3_i [7:0] $end
$var reg 4 A dec_bits_o [3:0] $end
$var reg 8 B path0_cand0 [7:0] $end
$var reg 8 C path0_cand1 [7:0] $end
$var reg 8 D path1_cand0 [7:0] $end
$var reg 8 E path1_cand1 [7:0] $end
$var reg 8 F path2_cand0 [7:0] $end
$var reg 8 G path2_cand1 [7:0] $end
$var reg 8 H path3_cand0 [7:0] $end
$var reg 8 I path3_cand1 [7:0] $end
$var reg 8 J pm_s0_o [7:0] $end
$var reg 8 K pm_s1_o [7:0] $end
$var reg 8 L pm_s2_o [7:0] $end
$var reg 8 M pm_s3_o [7:0] $end
$upscope $end
$scope task calculate_expected $end
$var reg 8 N c0 [7:0] $end
$var reg 8 O c1 [7:0] $end
$upscope $end
$scope task verify_all $end
$var reg 160 P scenario [160:1] $end
$upscope $end
$upscope $end
$enddefinitions $end
$comment Show the parameter values. $end
$dumpall
$end
#0
$dumpvars
bx P
bx O
bx N
b1111 M
b101 L
b10000 K
b110 J
b1111 I
b10100 H
b101 G
b1010 F
b10000 E
b10101 D
b110 C
b1011 B
b1111 A
b1111 @
b10100 ?
b101 >
b1010 =
b0 <
b1 ;
b0 :
b1 9
b0 8
b1 7
b0 6
b1 5
b1 4
b0 3
b1111 2
b10100 1
b101 0
b1010 /
bx .
b0 -
b1 ,
b0 +
b1 *
b0 )
b1 (
b0 '
b1 &
b1111 %
b110 $
b10000 #
b101 "
b1111 !
$end
#10000
b1111 .
b1111 O
b10100 N
b1001101011010010110111000100000010100000110000101110100011010000010000001000011011000010111001101100101 P
#11000
b11110 !
b11110 M
b1010 "
b1010 L
b11111 #
b11111 K
b1011 $
b1011 J
b1111 %
b1111 A
b11110 I
b101000 H
b1010 G
b10100 F
b11111 E
b101001 D
b1011 C
b10101 B
b11110 2
b11110 @
b101000 1
b101000 ?
b1010 0
b1010 >
b10100 /
b10100 =
b10 4
#21000
b11110 O
b101000 N
#22000
b101101 !
b101101 M
b1111 "
b1111 L
b101110 #
b101110 K
b10000 $
b10000 J
b1111 %
b1111 A
b101101 I
b111100 H
b1111 G
b11110 F
b101110 E
b111101 D
b10000 C
b11111 B
b101101 2
b101101 @
b111100 1
b111100 ?
b1111 0
b1111 >
b11110 /
b11110 =
b11 4
#32000
b101101 O
b111100 N
#33000
b111100 !
b111100 M
b10100 "
b10100 L
b111101 #
b111101 K
b10101 $
b10101 J
b1111 %
b1111 A
b111100 I
b1010000 H
b10100 G
b101000 F
b111101 E
b1010001 D
b10101 C
b101001 B
b111100 2
b111100 @
b1010000 1
b1010000 ?
b10100 0
b10100 >
b101000 /
b101000 =
b100 4
#43000
b111100 O
b1010000 N
#44000
b1001011 !
b1001011 M
b11001 "
b11001 L
b1001100 #
b1001100 K
b11010 $
b11010 J
b1111 %
b1111 A
b1001011 I
b1100100 H
b11001 G
b110010 F
b1001100 E
b1100101 D
b11010 C
b110011 B
b1001011 2
b1001011 @
b1100100 1
b1100100 ?
b11001 0
b11001 >
b110010 /
b110010 =
b101 4
#54000
b1001011 O
b1100100 N
#55000
b1001011 !
b1001011 M
b101 "
b101 L
b1001100 #
b1001100 K
b111 $
b111 J
b1010 %
b1010 A
b110010 G
b101 F
b110100 C
b111 B
b10 (
b10 7
b10 &
b10 5
b110010 0
b110010 >
b101 /
b101 =
b1 4
#65000
b1010 .
b1001011 O
b1100100 N
b1010011011101110110100101110100011000110110100001101001011011100110011100100000010101110110100101101110011011100110010101110010 P
#66000
b10 4
#76000
b1001011 O
b1100100 N
#77000
b1001011 !
b1001011 M
b101 "
b101 L
b1001100 #
b1001100 K
b111 $
b111 J
b1111 %
b1111 A
b101 G
b110010 F
b111 C
b110100 B
b101 0
b101 >
b110010 /
b110010 =
b11 4
#87000
b1111 .
b1001011 O
b1100100 N
#88000
b100 4
#98000
b1001011 O
b1100100 N
#99000
b101 4
#109000
b1001011 O
b1100100 N
#110000
b1001011 !
b1001011 M
b11111010 "
b11111010 L
b1001100 #
b1001100 K
b11111010 $
b11111010 J
b1011 %
b1011 A
b11111010 G
b11111010 F
b11111010 C
b11111011 B
b0 (
b0 7
b1 &
b1 5
b11111010 0
b11111010 >
b11111010 /
b11111010 =
b1 4
#120000
b1011 .
b1001011 O
b1100100 N
b1000010011011110111010101101110011001000110000101110010011110010010000001000011011000010111001101100101 P
#121000
b1001011 !
b1001011 M
b11111010 "
b11111010 L
b1001100 #
b1001100 K
b11111010 $
b11111010 J
b1011 %
b1011 A
b11111100 B
b10 &
b10 5
b10 4
#131000
b1001011 O
b1100100 N
#132000
b1001011 !
b1001011 M
b11111010 "
b11111010 L
b1001100 #
b1001100 K
b11111010 $
b11111010 J
b1011 %
b1011 A
b11111101 B
b11 &
b11 5
b11 4
#142000
b1001011 O
b1100100 N
#143000
b1001011 !
b1001011 M
b11111010 "
b11111010 L
b1001100 #
b1001100 K
b11111010 $
b11111010 J
b1010 %
b1010 A
b11111010 B
b0 &
b0 5
b100 4
#153000
b1010 .
b1001011 O
b1100100 N
#154000
b1001011 !
b1001011 M
b11111010 "
b11111010 L
b1001100 #
b1001100 K
b11111010 $
b11111010 J
b1011 %
b1011 A
b11111011 B
b1 &
b1 5
b101 4
#164000
b1011 .
b1001011 O
b1100100 N
#165000
b0 !
b0 M
b0 "
b0 L
b0 #
b0 K
b0 $
b0 J
b0 %
b0 A
b0 I
b0 H
b0 G
b0 F
b0 E
b0 D
b0 C
b0 B
b0 &
b0 5
b0 *
b0 9
b0 ,
b0 ;
b0 /
b0 =
b0 0
b0 >
b0 1
b0 ?
b0 2
b0 @
b1 4
#175000
b0 .
b0 O
b0 N
b10110100110010101110010011011110010000001000011011000010111001101100101 P
#176000
b10 4
#187000
b11 4
#198000
b100 4
#209000
b101 4
#220000
b1011 !
b1011 M
b100101 "
b100101 L
b1010 #
b1010 K
b100101 $
b100101 J
b1100100 I
b1011 H
b10000010 G
b100101 F
b1100101 E
b1010 D
b10000010 C
b100101 B
b1 -
b1 <
b10 +
b10 :
b1 )
b1 8
b1 '
b1 6
b10 ,
b10 ;
b1 *
b1 9
b1 (
b1 7
b1 &
b1 5
b1100011 2
b1100011 @
b1001 1
b1001 ?
b10000001 0
b10000001 >
b100100 /
b100100 =
b1 4
#230000
b1100100 O
b1011 N
b1010010011000010110111001100100011011110110110100100000010100110111010001110010011001010111001101110011 P
#231000
b1111 %
b1111 A
b11001000 !
b11001000 M
b10001111 "
b10001111 L
b11001001 #
b11001001 K
b10001110 $
b10001110 J
b11001000 I
b11111011 H
b10001111 G
b11101111 F
b11001001 E
b11111010 D
b10001110 C
b11101110 B
b10 -
b10 <
b11 )
b11 8
b10 '
b10 6
b11 ,
b11 ;
b10 (
b10 7
b11000110 2
b11000110 @
b11111001 1
b11111001 ?
b10001100 0
b10001100 >
b11101101 /
b11101101 =
b10 4
#241000
b1111 .
b11001000 O
b11111011 N
#242000
b1011110 !
b1011110 M
b11000101 "
b11000101 L
b1011111 #
b1011111 K
b11000110 $
b11000110 J
b101 %
b101 A
b10111110 I
b1011110 H
b11000101 G
b11101000 F
b10111111 E
b1011111 D
b11000110 C
b11101001 B
b1 -
b1 <
b0 )
b0 8
b0 '
b0 6
b10 ,
b10 ;
b11 *
b11 9
b1 (
b1 7
b10111101 2
b10111101 @
b1011100 1
b1011100 ?
b11000101 0
b11000101 >
b11101000 /
b11101000 =
b11 4
#252000
b101 .
b10111110 O
b1011110 N
#253000
b10000 !
b10000 M
b10110 "
b10110 L
b1111 #
b1111 K
b10100 $
b10100 J
b101 %
b101 A
b1010101 I
b10000 H
b10110 G
b10010111 F
b1010101 E
b1111 D
b10100 C
b10011001 B
b10 -
b10 <
b11 +
b11 :
b11 )
b11 8
b1 '
b1 6
b10 *
b10 9
b11 &
b11 5
b1010011 2
b1010011 @
b1101 1
b1101 ?
b10011 0
b10011 >
b10010110 /
b10010110 =
b100 4
#263000
b1010101 O
b10000 N
#264000
b10001100 !
b10001100 M
b111110 "
b111110 L
b10001011 #
b10001011 K
b111100 $
b111100 J
b1111 %
b1111 A
b10001100 I
b11110100 H
b111110 G
b11001101 F
b10001011 E
b11110010 D
b111100 C
b11001011 B
b10 +
b10 :
b10 )
b10 8
b11 '
b11 6
b1 ,
b1 ;
b0 *
b0 9
b0 (
b0 7
b1 &
b1 5
b10001010 2
b10001010 @
b11110010 1
b11110010 ?
b111100 0
b111100 >
b11001010 /
b11001010 =
b101 4
#274000
b1111 .
b10001100 O
b11110100 N
#275000
b110 4
